clusterfudge/__init__.py
clusterfudge/__main__.py
clusterfudge/cli.py
clusterfudge/clusterfudge.py
clusterfudge/sandboxes.py
clusterfudge_proto/__init__.py
clusterfudge_proto/exec/__init__.py
clusterfudge_proto/exec/exec_pb2.py
clusterfudge_proto/exec/exec_pb2.pyi
clusterfudge_proto/exec/exec_pb2_grpc.py
clusterfudge_proto/fudgelet/__init__.py
clusterfudge_proto/fudgelet/fudgelet_pb2.py
clusterfudge_proto/fudgelet/fudgelet_pb2.pyi
clusterfudge_proto/fudgelet/fudgelet_pb2_grpc.py
clusterfudge_proto/launches/__init__.py
clusterfudge_proto/launches/launches_pb2.py
clusterfudge_proto/launches/launches_pb2.pyi
clusterfudge_proto/launches/launches_pb2_grpc.py
clusterfudge_proto/logs/__init__.py
clusterfudge_proto/logs/logs_pb2.py
clusterfudge_proto/logs/logs_pb2.pyi
clusterfudge_proto/logs/logs_pb2_grpc.py
clusterfudge_proto/pagespb/__init__.py
clusterfudge_proto/pagespb/pages_pb2.py
clusterfudge_proto/pagespb/pages_pb2.pyi
clusterfudge_proto/pagespb/pages_pb2_grpc.py
clusterfudge_proto/resources/__init__.py
clusterfudge_proto/resources/resources_pb2.py
clusterfudge_proto/resources/resources_pb2.pyi
clusterfudge_proto/resources/resources_pb2_grpc.py
clusterfudge_proto/sandboxespb/__init__.py
clusterfudge_proto/sandboxespb/sandboxes_pb2.py
clusterfudge_proto/sandboxespb/sandboxes_pb2.pyi
clusterfudge_proto/sandboxespb/sandboxes_pb2_grpc.py
clusterfudge_proto/slurmpb/__init__.py
clusterfudge_proto/slurmpb/slurm_pb2.py
clusterfudge_proto/slurmpb/slurm_pb2.pyi
clusterfudge_proto/slurmpb/slurm_pb2_grpc.py
clusterfudge_proto/tunnelpb/__init__.py
clusterfudge_proto/tunnelpb/tunnel_pb2.py
clusterfudge_proto/tunnelpb/tunnel_pb2.pyi
clusterfudge_proto/tunnelpb/tunnel_pb2_grpc.py
clusterfudge-0.66.0.dist-info/METADATA
clusterfudge-0.66.0.dist-info/WHEEL
clusterfudge-0.66.0.dist-info/entry_points.txt
clusterfudge-0.66.0.dist-info/licenses/LICENSE
clusterfudge-0.66.0.dist-info/RECORD
